Workbook

Sheet Панель
A1: Маркетинговый бюджет Star Building · сентябрь–декабрь 2026
A3: Показатель | B3: План
A4: Операционный маркетинг | B4: =SUM('Помесячный бюджет'!B5:B8)
A5: Обязательная инфраструктура | B5: =SUM('Помесячный бюджет'!C5:C8)
A6: Разовое оборудование | B6: =SUM('Помесячный бюджет'!D5:D8)
A7: Общий предел | B7: =SUM('Помесячный бюджет'!F5:F8)
A8: Коммерческие возможности | B8: =SUM('KPI и рубежи'!D5:D8)
A9: Новая квалифицированная воронка, тонн | B9: =SUM('KPI и рубежи'!E5:E8)
A11: Принцип финансирования
A12: 450 → 650 → 850 → 1 050 тыс. ₸. Следующая ступень открывается только после проверки Битрикс24, качества возможностей и производственных ограничений.
A14: Ключевые ограничения
A15: • Лид считается квалифицированным только при наличии компании, объекта, региона, тоннажа, стадии, ЛПР и следующего шага.
A16: • После 100 000 ₸ расхода без квалифицированной возможности кампания останавливается.
A17: • Отраслевые СМИ запускаются только с отдельной посадочной страницей и измеряемой воронкой.
A18: • Маркетинг не обещает срок и объём без подтверждённого производственного слота.

Sheet Помесячный бюджет
A1: Помесячный предел бюджета
A4: Месяц | B4: Операционный маркетинг | C4: Инфраструктура | D4: Разовое оборудование | E4: Рост операционного бюджета | F4: Общий предел | G4: Факт | H4: Отклонение
A5: Сентябрь | B5: 450000 | C5: 16680 | D5: 180000 | E5: — | F5: =SUM(B5:D5) | H5: =IF(G5="","",G5-F5)
A6: Октябрь | B6: 650000 | C6: 18380 | D6: 0 | E6: =B6/B5-1 | F6: =SUM(B6:D6) | H6: =IF(G6="","",G6-F6)
A7: Ноябрь | B7: 850000 | C7: 7100 | D7: 0 | E7: =B7/B6-1 | F7: =SUM(B7:D7) | H7: =IF(G7="","",G7-F7)
A8: Декабрь | B8: 1050000 | C8: 7100 | D8: 0 | E8: =B8/B7-1 | F8: =SUM(B8:D8) | H8: =IF(G8="","",G8-F8)
A9: Итого | B9: =SUM(B5:B8) | C9: =SUM(C5:C8) | D9: =SUM(D5:D8) | F9: =SUM(F5:F8) | G9: =SUM(G5:G8) | H9: =IF(G9=0,"",G9-F9)

Sheet Детальный план
A1: Детальный план расходов и план/факт
A4: Месяц | B4: Статья | C4: План | D4: Факт | E4: Отклонение | F4: Ответственный | G4: Ожидаемый результат | H4: Условие запуска/масштабирования | I4: Статус | J4: Комментарий
A5: Сентябрь | B5: Поисковая реклама | C5: 150000 | E5: =IF(D5="","",D5-C5) | F5: Таргетолог + РОП | G5: Квалифицированные проектные обращения | H5: ≥1 квалифицированная возможность на 100 000 ₸ | I5: Запланировано
A6: Сентябрь | B6: Повторный показ и медийные тесты | C6: 20000 | E6: =IF(D6="","",D6-C6) | F6: Таргетолог | G6: Возврат посетителей отраслевых страниц | H6: Есть аудитория ≥300 посетителей | I6: Запланировано
A7: Сентябрь | B7: SEO и качественные внешние ссылки | C7: 37000 | E7: =IF(D7="","",D7-C7) | F7: SEO + веб-дизайнер | G7: Рост видимости и доверия доменов | H7: Аудит домена и перечень проверенных площадок | I7: Запланировано
A8: Сентябрь | B8: Экспертный контент и кейсы | C8: 45000 | E8: =IF(D8="","",D8-C8) | F8: Маркетинг + технический эксперт | G8: Кейсы, статьи и лид-магниты | H8: Фактология проверена техническим экспертом | I8: Запланировано
A9: Сентябрь | B9: Видео и творческие материалы | C9: 30000 | E9: =IF(D9="","",D9-C9) | F9: Мобилограф | G9: Доказательный видеоконтент | H9: Сценарий и объект согласованы | I9: Запланировано
A10: Сентябрь | B10: ABM, партнёры и экскурсии | C10: 50000 | E10: =IF(D10="","",D10-C10) | F10: Коммерческий директор + РОП | G10: Целевые встречи, партнёры и объекты | H10: Список целевых компаний и следующий шаг | I10: Запланировано
A11: Сентябрь | B11: Аналитика и посадочные страницы | C11: 70000 | E11: =IF(D11="","",D11-C11) | F11: Веб-дизайнер + аналитик | G11: Корректная атрибуция и конверсия страниц | H11: События и UTM перед запуском рекламы | I11: Запланировано
A12: Сентябрь | B12: ИИ и программные сервисы | C12: 25000 | E12: =IF(D12="","",D12-C12) | F12: Маркетинг | G12: Ускорение производства материалов | H12: Человеческая проверка каждого материала | I12: Запланировано
A13: Сентябрь | B13: Отраслевые СМИ | C13: 0 | E13: =IF(D13="","",D13-C13) | F13: Коммерческий директор | G13: Проверяемый доступ к отраслевым ЛПР | H13: Посадочная страница, UTM и отслеживаемый номер | I13: Запланировано
A14: Сентябрь | B14: Резерв и эксперименты | C14: 23000 | E14: =IF(D14="","",D14-C14) | F14: Коммерческий директор | G14: Проверка новых гипотез | H14: Письменная гипотеза и критерий остановки | I14: Запланировано
A15: Октябрь | B15: Поисковая реклама | C15: 230000 | E15: =IF(D15="","",D15-C15) | F15: Таргетолог + РОП | G15: Квалифицированные проектные обращения | H15: ≥1 квалифицированная возможность на 100 000 ₸ | I15: Запланировано
A16: Октябрь | B16: Повторный показ и медийные тесты | C16: 40000 | E16: =IF(D16="","",D16-C16) | F16: Таргетолог | G16: Возврат посетителей отраслевых страниц | H16: Есть аудитория ≥300 посетителей | I16: Запланировано
... A44: Декабрь | B44: Резерв и эксперименты | C44: 30000 | E44: =IF(D44="","",D44-C44) | F44: Коммерческий директор | G44: Проверка новых гипотез | H44: Письменная гипотеза и критерий остановки | I44: Запланировано

Sheet KPI и рубежи
A1: Показатели и условия перехода к следующей ступени
A4: Месяц | B4: Все обращения | C4: Маркетингово квалифицированные | D4: Коммерческие возможности | E4: Новая воронка, тонн | F4: Стоимость возможности | G4: Стоимость тонны воронки | H4: Заполнение Битрикс24 | I4: Срок реакции | J4: Условие перехода | K4: Решение
A5: Сентябрь | B5: 15 | C5: 6 | D5: 2 | E5: 80 | F5: ='Помесячный бюджет'!B5/D5 | G5: ='Помесячный бюджет'!B5/E5 | H5: 0.95 | I5: ≤1 рабочего дня | J5: Настроена аналитика; ≥2 возможностей; 95% карточек заполнены | K5: Проверить по факту
A6: Октябрь | B6: 22 | C6: 9 | D6: 3 | E6: 150 | F6: ='Помесячный бюджет'!B6/D6 | G6: ='Помесячный бюджет'!B6/E6 | H6: 0.95 | I6: ≤1 рабочего дня | J6: ≥3 возможностей; есть первая атрибуция каналов; производство подтверждает приоритетные сегменты | K6: Проверить по факту
A7: Ноябрь | B7: 30 | C7: 12 | D7: 4 | E7: 220 | F7: ='Помесячный бюджет'!B7/D7 | G7: ='Помесячный бюджет'!B7/E7 | H7: 0.95 | I7: ≤1 рабочего дня | J7: ≥4 возможностей; стоимость возможности ≤225 тыс. ₸; отраслевой пилот измерим | K7: Проверить по факту
A8: Декабрь | B8: 38 | C8: 15 | D8: 5 | E8: 300 | F8: ='Помесячный бюджет'!B8/D8 | G8: ='Помесячный бюджет'!B8/E8 | H8: 0.95 | I8: ≤1 рабочего дня | J8: ≥5 возможностей; сформирована воронка 300 т; утверждён план I квартала 2027 | K8: Проверить по факту

Sheet Аудит исходника
A1: Аудит файла «Маркетинговый бюджет.xlsx»
A4: № | B4: Наблюдение | C4: Риск | D4: Рекомендация | E4: Приоритет | F4: Статус
A5: 1 | B5: Три медиаплана: 235 216 / 482 583 / 708 820 ₸ | C5: Это только платный трафик, без полного маркетингового контура | D5: Использовать как исходную гипотезу, заменить фактом Битрикс24 | E5: Высокий | F5: Открыто
A6: 2 | B6: Прогноз 59–170 лидов | C6: Не определено качество лида и отсутствует фактическая конверсия | D6: Считать коммерческие возможности и квалифицированные тонны | E6: Критический | F6: Открыто
A7: 3 | B7: Аудитория M-W 25–55, Казахстан кроме запада | C7: Слишком широкая сегментация для проектного B2B | D7: Сегментировать по отраслям, объектам, ролям и регионам | E7: Высокий | F7: Открыто
A8: 4 | B8: Google/Яндекс рассчитаны в USD по курсу 488 | C8: Не учтены курс, НДС, комиссия и сопровождение | D8: Вести утверждённый предел в тенге; комиссии — отдельными строками | E8: Средний | F8: Открыто
A9: 5 | B9: 74 000 ₸ на внешние ссылки | C9: Неясно: на один сайт или на оба; нет перечня площадок | D9: Начать с пилота 37 000 ₸ и масштабировать после аудита | E9: Высокий | F9: Открыто
A10: 6 | B10: ElDala: баннеры, статья, новость | C10: Охват площадки не равен квалифицированным объектам | D10: Только пилот с UTM, посадочной страницей и стоп-критерием | E10: Высокий | F10: Открыто
A11: 7 | B11: Телефон от 180 000 ₸ | C11: Нет технического задания и критерия выбора | D11: Утвердить спецификацию и лимит до покупки | E11: Средний | F11: Открыто
A12: 8 | B12: Зарплата мобилографа не указана | C12: Нельзя определить полный бюджет функции | D12: Вынести фонд оплаты труда отдельным решением | E12: Высокий | F12: Открыто
A13: 9 | B13: Нет план/факта и правил остановки | C13: Расходы могут расти без результата | D13: Ежемесячный комитет и контрольные рубежи | E13: Критический | F13: Открыто
A14: 10 | B14: Нет связи с производственными слотами | C14: Маркетинг может создать неисполнимый спрос | D14: Синхронизировать сегменты и обещания с производством | E14: Критический | F14: Открыто

Sheet Контент-план
A1: Контент и доказательства для поддержки бюджета
A4: Месяц | B4: Материал | C4: Формат | D4: Целевой сегмент | E4: Ответственный | F4: Призыв к действию | G4: Показатель | H4: Статус
A5: Сентябрь | B5: ЛСТК против традиционного строительства: честный разбор | C5: Статья + карусель | D5: Промышленность/склады | E5: Маркетинг + инженер | F5: Получить предварительный разбор объекта | G5: Квалифицированные обращения | H5: В планах
A6: Сентябрь | B6: Гид: 7 вопросов заводу перед договором | C6: Лид-магнит | D6: Все B2B | E6: Маркетинг + РОП | F6: Скачать после формы с объектом и тоннажем | G6: Заполненные формы | H6: В планах
A7: Сентябрь | B7: Экскурсия на производство | C7: Видео + очное событие | D7: Генподрядчики/проектировщики | E7: Мобилограф + РОП | F7: Записаться на техническую встречу | G7: Участники и встречи | H7: В планах
A8: Октябрь | B8: Сделано в Казахстане: 5 причин | C8: Статья + видео | D8: Агро/промышленность | E8: Маркетинг | F8: Запросить расчёт | G8: Возможности | H8: В планах
A9: Октябрь | B9: С-профиль, Сигма, Z или П-профиль | C9: Технический разбор | D9: Проектировщики | E9: Инженер + маркетинг | F9: Запросить узлы | G9: Проектные контакты | H9: В планах
A10: Октябрь | B10: Стройка зимой | C10: Видео-кейс | D10: Склады/агро | E10: Мобилограф + производство | F10: Обсудить зимний график | G10: Встречи | H10: В планах
A11: Ноябрь | B11: Быстровозводимые здания для сельского хозяйства | C11: Отраслевая страница | D11: Агропром | E11: Веб-дизайнер + КД | F11: Получить отраслевое предложение | G11: Тонны воронки | H11: В планах
A12: Ноябрь | B12: Точка росы и конденсат | C12: Вебинар | D12: Склады/агро | E12: Инженер + РОП | F12: Записаться на консультацию | G12: SQL | H12: В планах
A13: Ноябрь | B13: Реальный кейс экономии на фундаменте | C13: Кейс с проверенными цифрами | D13: Собственники объектов | E13: КД + инженер | F13: Получить сравнение вариантов | G13: Возможности | H13: В планах
A14: Декабрь | B14: Каркас + сэндвич-панели | C14: Комплект решения | D14: Промышленность/логистика | E14: Коммерческий блок | F14: Запросить тёплый контур | G14: Средний тоннаж | H14: В планах
A15: Декабрь | B15: Сейсмостойкость ЛСТК | C15: Технический материал | D15: Юг Казахстана | E15: Технический блок | F15: Техническая встреча | G15: Проектные контакты | H15: В планах
A16: Декабрь | B16: Итоги года: производство, люди, объекты | C16: Документальный ролик | D16: Все сегменты | E16: Мобилограф + КД | F16: Запланировать объект 2027 | G16: Воронка I кв. 2027 | H16: В планах

Sheet Допущения
A1: Допущения, исключения и вопросы для утверждения
A4: Параметр | B4: Принято в модели | C4: Что требуется уточнить | D4: Влияние
A5: Период | B5: Сентябрь–декабрь 2026 | C5: — | D5: План на четыре месяца
A6: Операционный бюджет | B6: 3 000 000 ₸ | C6: Утверждение Генерального директора | D6: Предел расходов
A7: Инфраструктура | B7: Хостинг 7 100 ₸/мес.; домены по датам исходника | C7: Подтвердить факт уже произведённых оплат | D7: Может снизить остаток
A8: Телефон мобилографа | B8: До 180 000 ₸ | C8: Техническое задание и модель | D8: Разовый капвклад
A9: Фонд оплаты труда | B9: Не включён | C9: Зарплаты и налоги действующего/нового штата | D9: Добавляется сверх модели
A10: НДС и комиссии | B10: Не включены | C10: Условия подрядчиков и рекламных кабинетов | D10: Добавляются отдельной строкой
A11: SEO-ссылки | B11: 37 тыс. ₸ пилот; затем 74–100 тыс. ₸ | C11: 74 тыс. ₸ относится к одному или двум сайтам | D11: Может изменить SEO-бюджет
A12: Курс USD/KZT | B12: В новой модели лимиты фиксируются в тенге | C12: Курс оплаты зарубежных сервисов | D12: Поглощается резервом до его предела
A13: Лиды исходника | B13: Не используются как гарантированный прогноз | C13: Фактические данные Битрикс24 за 2 месяца | D13: Заменят целевые KPI
A14: Производственная мощность | B14: 500 т/мес. — целевое состояние | C14: Фактическая мощность, слоты, персонал | D14: Ограничивает масштабирование рекламы
